aiohydroottawa/__init__.py
aiohydroottawa/aws_srp.py
aiohydroottawa/exceptions.py
aiohydroottawa/hydro_ottawa.py
aiohydroottawa/models.py
aiohydroottawa/py.typed
aiohydroottawa-0.3.0.dist-info/LICENSE
aiohydroottawa-0.3.0.dist-info/METADATA
aiohydroottawa-0.3.0.dist-info/WHEEL
aiohydroottawa-0.3.0.dist-info/RECORD
