Metadata-Version: 2.1
Name: aiohydroottawa
Version: 0.3.0
Summary: 
Author: Carter Green
Author-email: carter.green@icloud.com
Requires-Python: >=3.11,<4.0
Classifier: Framework :: AsyncIO
Classifier: Intended Audience :: Developers
Classifier: Natural Language :: English
Classifier: Programming Language :: Python :: 3
Classifier: Programming Language :: Python :: 3.11
Classifier: Programming Language :: Python :: 3.12
Classifier: Programming Language :: Python :: 3.13
Classifier: Topic :: Software Development :: Libraries :: Python Modules
Requires-Dist: aiohttp (>=3.10.2,<4.0.0)
Requires-Dist: boto3 (>=1.33.7,<2.0.0)
Requires-Dist: mashumaro (>=3.13,<4.0)
